propertybag/PROJECT.txt
propertybag/__init__.py
propertybag/propertybag.py
propertybag-0.1.9.dist-info/LICENSE
propertybag-0.1.9.dist-info/METADATA
propertybag-0.1.9.dist-info/WHEEL
propertybag-0.1.9.dist-info/top_level.txt
propertybag-0.1.9.dist-info/RECORD
