Metadata-Version: 2.1
Name: propertybag
Version: 0.1.9
Summary: Flexible property bag functions
Home-page: https://github.com/wheresjames/propertybag
Author: Robert Umbehant
Author-email: propertybag@wheresjames.com
License: MIT
Platform: UNKNOWN
